cpr/__init__.py
cpr/f1p.py
F1Project-1.0.3.dist-info/METADATA
F1Project-1.0.3.dist-info/WHEEL
F1Project-1.0.3.dist-info/top_level.txt
F1Project-1.0.3.dist-info/RECORD
