Metadata-Version: 2.1
Name: F1Project
Version: 1.0.3
Summary: Primer proyecto de paquete
Home-page: https://fouen.github.io
Author: Fouen
